{
  "type": "Prerender",
  "expiration": false,
  "group": 17,
  "bypassToken": "d0555888e36b126ad33fd7c33d9589a1",
  "experimentalBypassFor": [
    {
      "type": "header",
      "key": "Next-Action"
    },
    {
      "type": "header",
      "key": "content-type",
      "value": "multipart/form-data;.*"
    }
  ],
  "fallback": {
    "type": "FileFsRef",
    "mode": 33188,
    "fsPath": "outline.rsc.prerender-fallback.rsc"
  },
  "initialHeaders": {
    "x-next-cache-tags": "_N_T_/layout,_N_T_/(presentation-generator)/layout,_N_T_/(presentation-generator)/outline/layout,_N_T_/(presentation-generator)/outline/page,_N_T_/outline",
    "vary": "RSC, Next-Router-State-Tree, Next-Router-Prefetch",
    "content-type": "text/x-component"
  },
  "allowQuery": []
}
